cds10_aidh/__init__.py
cds10_aidh/cli.py
cds10_aidh/commandments.py
cds10_aidh/ingest.py
cds10_aidh/schema.py
cds10_aidh/scoring.py
cds10_aidh/viz.py
cds10_aidh-0.1.5.dist-info/licenses/LICENSE
cds10_aidh-0.1.5.dist-info/METADATA
cds10_aidh-0.1.5.dist-info/WHEEL
cds10_aidh-0.1.5.dist-info/entry_points.txt
cds10_aidh-0.1.5.dist-info/top_level.txt
cds10_aidh-0.1.5.dist-info/RECORD
