Metadata-Version: 2.4
Name: cds10-aidh
Version: 0.1.5
Summary: CDS Ten Commandments audit: scoring, recommendations, visuals, URL/YAML input
Author: cds10-aidh authors
License: MIT
Classifier: Programming Language :: Python :: 3
Classifier: License :: OSI Approved :: MIT License
Classifier: Topic :: Scientific/Engineering :: Medical Science Apps.
Requires-Python: >=3.9
License-File: LICENSE
Requires-Dist: pydantic>=2
Requires-Dist: pyyaml>=6
Requires-Dist: matplotlib>=3.7
Provides-Extra: ingest
Requires-Dist: requests>=2.31; extra == "ingest"
Requires-Dist: beautifulsoup4>=4.12; extra == "ingest"
Requires-Dist: readability-lxml>=0.8.1; extra == "ingest"
Dynamic: license-file
